{"url":{"scheme":"http","host":"uconn.edu","original":"http:\/\/uconn.edu","base":"http:\/\/uconn.edu"},"snapshot_info":{"ts":1429415850,"version":1,"date":"2015-04-18"},"domain":{"name":"uconn.edu","tld":"edu","ipv4":"137.99.25.178","whois":{"regrinfo":{"owner":{"name":"University of Connecticut","address":{"0":"University Information Technology Services","1":"369 Fairfield Road, Unit 2209","2":"Storrs, CT 06269-2209","3":"UNITED STATES"}},"admin":{"phone":"+1-860-486-8867","email":"jeffrey.farese@uconn.edu","name":"Jeffrey Farese","address":{"0":"Network Security Analyst","1":"University Information Technology Services","2":"196 Auditorium Road, Unit 3138","3":"Storrs, CT 06269-2209","4":"UNITED STATES"}},"tech":{"phone":"+1-860-486-8867","email":"jeffrey.farese@uconn.edu","name":"Jeffrey Farese","address":{"0":"Network Security Analyst","1":"University Information Technology Services","2":"196 Auditorium Road, Unit 3138","3":"Storrs, CT 06269-2209","4":"UNITED STATES"}},"domain":{"nserver":{"msb-cache.net.uconn.edu":"137.99.25.11","hbl-cache.net.uconn.edu":"137.99.203.22","dr-dns.net.uconn.edu":"67.218.95.47"},"created":"1987-08-18","changed":"2013-06-07","name":"uconn.edu"},"registered":"yes"}}},"server":{"server":{"raw":"Apache\/2.2.16 (Debian)"},"cms":"Powered by Visual Composer - drag and drop page builder for WordPress."},"response":{"time":0.49,"status":"200","protocol":"HTTP\/1.1","message":"OK","headers":{"date":"Sun, 19 Apr 2015 03:57:29 GMT","server":"Apache\/2.2.16 (Debian)","last-modified":"Sun, 19 Apr 2015 03:04:09 GMT","etag":"\"600d38-df78-5140b113b75c3\"","accept-ranges":"bytes","content-length":"57208","vary":"Accept-Encoding,Cookie","x-ua-compatible":"IE=edge","x-powered-by":"W3 Total Cache\/0.9.4","pragma":"public","cache-control":"public, public","connection":"close","content-type":"text\/html; charset=UTF-8"}},"content":{"title":" University of Connecticut","meta_tags":{"generator":"Powered by Visual Composer - drag and drop page builder for WordPress."},"analysis":{"text":{"counts":{"word":803,"sentence":36,"avg_sentance_words":23},"tags":{"word_weights":{"uconn":{"count":15,"weight":7},"campus":{"count":14,"weight":7},"students":{"count":13,"weight":6},"research":{"count":8,"weight":4},"health":{"count":7,"weight":3},"resources":{"count":6,"weight":3},"connecticut":{"count":6,"weight":3},"prospective":{"count":5,"weight":2},"opportunities":{"count":5,"weight":2},"university":{"count":5,"weight":2},"academic":{"count":4,"weight":2},"campuses":{"count":4,"weight":2},"history":{"count":4,"weight":2},"visit":{"count":4,"weight":2},"schools":{"count":4,"weight":2},"colleges":{"count":4,"weight":2},"culture":{"count":4,"weight":2},"life":{"count":4,"weight":2},"academics":{"count":3,"weight":1},"study":{"count":3,"weight":1},"athletics":{"count":3,"weight":1},"student":{"count":3,"weight":1},"based":{"count":3,"weight":1},"living":{"count":3,"weight":1},"activities":{"count":3,"weight":1}}},"readability":{"flesch_kincaid_reading_ease":24.8,"gunning_fog_score":14.1,"coleman_liau_index":17,"smog_index":13.9,"automated_readability_index":16.4}},"html":{"dom":{"counts":{"tags":{"div":139,"a":126,"li":122,"img":28,"ul":23,"script":22,"h2":16,"p":14,"span":13,"link":11,"comment":8,"nav":7,"style":6,"meta":4,"br":4,"h1":4,"section":3,"h4":2,"footer":1,"article":1,"header":1,"head":1,"body":1,"html":1,"title":1,"input":1,"label":1},"total":553},"body":{"count":2,"children":{"0":"a","1":"div"},"hash":"330990eacf54a05515ed771ba3d27804","note":"I should be able to use this to get a feel for major redesigns?"}},"page_size":57281,"amazon":{"alexa":{"dmoz":{"0":"Reference","1":"Education","2":"Colleges and Universities","3":"North America","4":"United States","5":"Connecticut","6":"University of Connecticut"},"stats":{"speed":"733","links_in":"14679","reach":"11359","popularity":"10042","delta":"-810"},"related_links":{"edu":{"http:\/\/www.wciu.edu\/":{"HREF":"http:\/\/www.wciu.edu\/","TITLE":"William Carey International University","PARSED_LINK":{"scheme":"http","host":"www.wciu.edu","path":"\/"}},"http:\/\/www.udel.edu\/":{"HREF":"http:\/\/www.udel.edu\/","TITLE":"University of Delaware","PARSED_LINK":{"scheme":"http","host":"www.udel.edu","path":"\/"}},"http:\/\/www.learn.unh.edu\/":{"HREF":"http:\/\/www.learn.unh.edu\/","TITLE":"University of New Hampshire Continuing Education","PARSED_LINK":{"scheme":"http","host":"www.learn.unh.edu","path":"\/"}},"http:\/\/www.hnet.uci.edu\/philosophy":{"HREF":"http:\/\/www.hnet.uci.edu\/philosophy","TITLE":"Uci Philosophy Home","PARSED_LINK":{"scheme":"http","host":"www.hnet.uci.edu","path":"\/philosophy"}},"http:\/\/www.ufl.edu\/":{"HREF":"http:\/\/www.ufl.edu\/","TITLE":"University of Florida","PARSED_LINK":{"scheme":"http","host":"www.ufl.edu","path":"\/"}},"http:\/\/www.uchc.edu\/":{"HREF":"http:\/\/www.uchc.edu\/","TITLE":"University of Connecticut Health Center","PARSED_LINK":{"scheme":"http","host":"www.uchc.edu","path":"\/"}},"http:\/\/www.yale.edu\/":{"HREF":"http:\/\/www.yale.edu\/","TITLE":"Yale University | Yale University","PARSED_LINK":{"scheme":"http","host":"www.yale.edu","path":"\/"}}}},"keywords":{"0":"University of Connecticut"}}},"validation":{"w3c":{"status":"Invalid","errors":"27","warnings":"7","process_duration":1429415870.02}},"google":{"page_speed":{"kind":"pagespeedonline#result","id":"http:\/\/uconn.edu\/","responseCode":200,"title":"University of Connecticut","score":60,"pageStats":{"numberResources":87,"numberHosts":8,"totalRequestBytes":"9246","numberStaticResources":46,"htmlResponseBytes":"57649","cssResponseBytes":"369660","imageResponseBytes":"3316674","javascriptResponseBytes":"486784","otherResponseBytes":"338859","numberJsResources":18,"numberCssResources":9}},"page_rank":{"error":{"note":"Error Loading Google Data","code":"403","message":"Forbidden"}}}}},"icon":{"tiny":"http:\/\/uconn.edu\/favicon.ico","default":"http:\/\/uconn.edu\/favicon.ico"},"h1":"  UCONN University of Connecticut ","screenshots":{"bluga":{"image_height":" 768"}}},"see_also":{"builtwith":"http:\/\/builtwith.com\/uconn.edu","netcraft":"http:\/\/uptime.netcraft.com\/up\/graph?site=uconn.edu","alexa":"http:\/\/www.alexa.com\/data\/details\/main\/uconn.edu","compete":"http:\/\/siteanalytics.compete.com\/uconn.edu","quantcast":"https:\/\/www.quantcast.com\/uconn.edu","w3valid":"http:\/\/validator.w3.org\/check?uri=http%3A%2F%2Fuconn.edu"},"process_duration":24.18}