{"url":{"scheme":"http","host":"www.apsu.edu","original":"http:\/\/www.apsu.edu","base":"http:\/\/www.apsu.edu"},"snapshot_info":{"ts":1429445714,"version":1,"date":"2015-04-19"},"domain":{"name":"apsu.edu","tld":"edu","ipv4":"198.146.56.2","whois":{"regrinfo":{"owner":{"name":"Austin Peay State University","address":{"0":"601 College Street","1":"Clarksville, TN 37044","2":"UNITED STATES"}},"admin":{"phone":"(931) 221-7588","email":"wallc@apsu.edu","name":"Charles B. Wall","address":{"0":"Austin Peay State University","1":"601 College Street","2":"Clarksville, TN 37044","3":"UNITED STATES"}},"tech":{"phone":"(931) 221-7113","email":"taylors@apsu.edu","name":"Stephanie Taylor","address":{"0":"Austin Peay State University","1":"601 College Street","2":"Clarksville, TN 37044","3":"UNITED STATES"}},"domain":{"nserver":{"apbrns1.apsu.edu":"198.146.56.200","apbrns2.apsu.edu":"198.146.56.201","ns1.tbr.edu":"198.146.12.10","ns1.tec.net":"198.146.3.1","ns2.tbr.edu":"141.225.215.120"},"created":"1993-07-13","changed":"2011-05-26","name":"apsu.edu"},"registered":"yes"}}},"server":{"server":{"raw":"Apache\/2.2.12 (Ubuntu)"}},"response":{"time":0.42,"status":"200","protocol":"HTTP\/1.1","message":"OK","headers":{"date":"Sun, 19 Apr 2015 12:15:15 GMT","server":"Apache\/2.2.12 (Ubuntu)","x-powered-by":"PHP\/5.2.10-2ubuntu6.10","set-cookie":"SESS68c8580e97ada06859b4303a7d14bed1=b29b8188551b12f79ce3e7572c826879; expires=Sun, 19-Apr-2015 22:15:15 GMT; path=\/; domain=.apsu.edu","last-modified":"Sun, 19 Apr 2015 11:49:17 GMT","etag":"\"3685888ec2fd7fca208b180fbb149f2d\"","expires":"Sun, 19 Nov 1978 05:00:00 GMT","cache-control":"must-revalidate","vary":"Accept-Encoding","connection":"close","content-type":"text\/html; charset=utf-8"}},"content":{"title":"Austin Peay State University | Middle Tennessee","description":"Austin Peay State University (APSU), located in Clarksville, Tennessee, is the state's fastest growing university. We are home to the Govs and Lady Govs.","meta_tags":{"description":"Austin Peay State University (APSU), located in Clarksville, Tennessee, is the state's fastest growing university. We are home to the Govs and Lady Govs.","keywords":"tennessee,austin peay,APSU,state,governors,govs,lady govs,universities,college,colleges,university,fastest growing,military,online,four year,4 year,liberal arts,physics,nursing,education,business,art,chemical engineering technology","google-site-verification":"Bs8Wq4_y0Wdo_kAxjK6igE56gpAI0v_uGul8zWQoIZk","msvalidate.01":"7B9F1F19E346A430B9EFFB1BCD698E17"},"analysis":{"text":{"counts":{"word":363,"sentence":15,"avg_sentance_words":27},"tags":{"word_weights":{"apsu":{"count":9,"weight":7},"university":{"count":6,"weight":5},"campus":{"count":5,"weight":4},"apr":{"count":5,"weight":4},"austin":{"count":5,"weight":4},"students":{"count":4,"weight":3},"peay":{"count":4,"weight":3},"visit":{"count":4,"weight":3},"news":{"count":4,"weight":3},"center":{"count":4,"weight":3},"events":{"count":3,"weight":2},"uc":{"count":3,"weight":2},"3:00pm":{"count":3,"weight":2},"5:00":{"count":3,"weight":2},"3:00":{"count":3,"weight":2},"annual":{"count":2,"weight":1},"feed":{"count":2,"weight":1},"rss":{"count":2,"weight":1},"raffle":{"count":2,"weight":1},"look":{"count":2,"weight":1},"scholarship":{"count":2,"weight":1},"6:00":{"count":2,"weight":1},"schedule":{"count":2,"weight":1},"foy":{"count":2,"weight":1},"meeting":{"count":2,"weight":1}},"meta_kw":{"0":"tennessee","1":"austin peay","2":"APSU","3":"state","4":"governors","5":"govs","6":"lady govs","7":"universities","8":"college","9":"colleges","10":"university","11":"fastest growing","12":"military","13":"online","14":"four year","15":"4 year","16":"liberal arts","17":"physics","18":"nursing","19":"education","20":"business","21":"art","22":"chemical engineering technology"}},"readability":{"flesch_kincaid_reading_ease":38.3,"gunning_fog_score":12.8,"coleman_liau_index":10,"smog_index":11.3,"automated_readability_index":12.6}},"html":{"dom":{"counts":{"tags":{"div":105,"a":77,"img":35,"li":33,"span":24,"comment":23,"p":8,"ul":7,"meta":7,"h5":6,"script":6,"input":6,"br":5,"td":4,"link":3,"tr":2,"h2":2,"table":1,"tbody":1,"form":1,"body":1,"style":1,"title":1,"h1":1,"html":1,"head":1,"label":1},"total":340},"body":{"count":5,"children":{"0":"div","1":"comment","2":"script","3":"script","4":"script"},"hash":"ae559c5527fd645cad25ecdc9b1b598a","note":"I should be able to use this to get a feel for major redesigns?"}},"page_size":31121,"amazon":{"alexa":{"dmoz":{"0":"Reference","1":"Education","2":"Colleges and Universities","3":"North America","4":"United States","5":"Tennessee","6":"Austin Peay State University"},"stats":{"speed":"949","links_in":"1432","reach":"83150","popularity":"65547","delta":"-9143"},"related_links":{"edu":{"http:\/\/www.aurora.edu\/":{"HREF":"http:\/\/www.aurora.edu\/","TITLE":"Aurora University","PARSED_LINK":{"scheme":"http","host":"www.aurora.edu","path":"\/"}},"http:\/\/www.bsu.edu\/":{"HREF":"http:\/\/www.bsu.edu\/","TITLE":"Ball State University","PARSED_LINK":{"scheme":"http","host":"www.bsu.edu","path":"\/"}},"http:\/\/www.bakeru.edu\/":{"HREF":"http:\/\/www.bakeru.edu\/","TITLE":"Baker University","PARSED_LINK":{"scheme":"http","host":"www.bakeru.edu","path":"\/"}},"http:\/\/www.babson.edu\/":{"HREF":"http:\/\/www.babson.edu\/","TITLE":"Babson College","PARSED_LINK":{"scheme":"http","host":"www.babson.edu","path":"\/"}},"http:\/\/www.avila.edu\/":{"HREF":"http:\/\/www.avila.edu\/","TITLE":"Avila University","PARSED_LINK":{"scheme":"http","host":"www.avila.edu","path":"\/"}},"http:\/\/www.averett.edu\/":{"HREF":"http:\/\/www.averett.edu\/","TITLE":"Averett University","PARSED_LINK":{"scheme":"http","host":"www.averett.edu","path":"\/"}},"http:\/\/www.augustana.edu\/":{"HREF":"http:\/\/www.augustana.edu\/","TITLE":"Augustana College","PARSED_LINK":{"scheme":"http","host":"www.augustana.edu","path":"\/"}},"http:\/\/www.augsburg.edu\/":{"HREF":"http:\/\/www.augsburg.edu\/","TITLE":"Augsburg College","PARSED_LINK":{"scheme":"http","host":"www.augsburg.edu","path":"\/"}},"http:\/\/www.augie.edu\/":{"HREF":"http:\/\/www.augie.edu\/","TITLE":"Augustana College","PARSED_LINK":{"scheme":"http","host":"www.augie.edu","path":"\/"}},"http:\/\/www.auburn.edu\/":{"HREF":"http:\/\/www.auburn.edu\/","TITLE":"Auburn University","PARSED_LINK":{"scheme":"http","host":"www.auburn.edu","path":"\/"}},"http:\/\/www.leecollege.edu\/":{"HREF":"http:\/\/www.leecollege.edu\/","TITLE":"www.leecollege.edu\/","PARSED_LINK":{"scheme":"http","host":"www.leecollege.edu","path":"\/"}}}},"keywords":{"0":"Austin Peay State University"}}},"validation":{"w3c":{"status":"Invalid","errors":"8","warnings":"0","process_duration":1429445728.62}},"google":{"page_speed":{"kind":"pagespeedonline#result","id":"http:\/\/www.apsu.edu\/","responseCode":200,"title":"Austin Peay State University | Middle Tennessee","score":74,"pageStats":{"numberResources":53,"numberHosts":2,"totalRequestBytes":"5554","numberStaticResources":50,"htmlResponseBytes":"31642","textResponseBytes":"915","cssResponseBytes":"85078","imageResponseBytes":"1849030","javascriptResponseBytes":"254360","numberJsResources":3,"numberCssResources":2}},"page_rank":{"error":{"note":"Error Loading Google Data","code":"403","message":"Forbidden"}}}}},"icon":{"tiny":"http:\/\/www.apsu.edu\/sites\/apsu.edu\/themes\/custom\/apsu\/favicon.ico","default":"http:\/\/www.apsu.edu\/sites\/apsu.edu\/themes\/custom\/apsu\/favicon.ico"},"h1":"Austin Peay State University | Middle Tennessee","screenshots":{"bluga":{"image_height":" 1329"}}},"see_also":{"builtwith":"http:\/\/builtwith.com\/www.apsu.edu","netcraft":"http:\/\/uptime.netcraft.com\/up\/graph?site=www.apsu.edu","alexa":"http:\/\/www.alexa.com\/data\/details\/main\/www.apsu.edu","compete":"http:\/\/siteanalytics.compete.com\/www.apsu.edu","quantcast":"https:\/\/www.quantcast.com\/www.apsu.edu","w3valid":"http:\/\/validator.w3.org\/check?uri=http%3A%2F%2Fwww.apsu.edu"},"process_duration":17.59}