{"url":{"scheme":"http","host":"www.msstate.edu","original":"http:\/\/www.msstate.edu","base":"http:\/\/www.msstate.edu"},"snapshot_info":{"ts":1429430005,"version":1,"date":"2015-04-19"},"domain":{"name":"msstate.edu","tld":"edu","ipv4":"130.18.80.20","ipv6":"2620::1a30:80:0:0:0:20","whois":{"regrinfo":{"owner":{"name":"Mississippi State University","address":{"0":"P.O. Box 9697","1":"175 President's Circle, Room 117","2":"Mississippi State, MS 39762","3":"UNITED STATES"}},"admin":{"phone":"(662) 325-9311","email":"jay.burrell@msstate.edu","name":"Jay G Burrell","address":{"0":"Director of Information Technology Infrastructure","1":"Mississippi State University","2":"P. O. Box 9697","3":"Mississippi State, MS 39762","4":"UNITED STATES"}},"tech":{"phone":"(662) 325-9311","email":"ssladmin@msstate.edu","name":"Gerhard M Lehnerer","address":{"0":"Manager of Network Services","1":"Mississippi State University","2":"PO Box 9697","3":"Mississippi State, MS 39762","4":"UNITED STATES"}},"domain":{"nserver":{"ns1.msstate.edu":"130.18.80.12","ns2.msstate.edu":"130.18.80.13","trantor.umd.edu":"128.8.10.14"},"created":"1988-09-22","changed":"2015-03-09","name":"msstate.edu"},"registered":"yes"}}},"server":{"server":{"raw":"Apache\/2.2.15 (Red Hat)"}},"response":{"time":0.34,"status":"200","protocol":"HTTP\/1.1","message":"OK","headers":{"date":"Sun, 19 Apr 2015 07:53:24 GMT","server":"Apache\/2.2.15 (Red Hat)","x-powered-by":"PHP\/5.3.3","cache-control":"no-cache","connection":"close","content-type":"text\/html; charset=UTF-8"}},"content":{"title":"Mississippi State University","description":"A land-grant university offering degrees through the doctoral level, Mississippi State University is the largest university in the state.","meta_tags":{"description":"A land-grant university offering degrees through the doctoral level, Mississippi State University is the largest university in the state.","keywords":"higher education, university, college, Mississippi State University, engineering, veterinary medicine, architecture, business, teacher education, agriculture, forestry","Owner":"Mississippi State University","dc.creator.e-mail":"msuinfo@ur.msstate.edu","geo.position":"33.273;-88.475","geo.placename":"Mississippi State, Mississippi","geo.country":"US","dmoz.id":"Reference\/Education\/Colleges_and_Universities\/North_America\/United_States\/Mississippi\/Mississippi_State_University","verify-v1":"thcPBLtDHAcIIqbl4UUFJ0eQhu38HTjzn3Xe2FV+zFk="},"analysis":{"text":{"counts":{"word":338,"sentence":4,"avg_sentance_words":89},"tags":{"word_weights":{"msu":{"count":9,"weight":7},"faculty":{"count":4,"weight":3},"news":{"count":3,"weight":2},"campus":{"count":3,"weight":2},"events":{"count":3,"weight":2},"conservation":{"count":3,"weight":2},"status":{"count":3,"weight":2},"students":{"count":3,"weight":2},"online":{"count":3,"weight":2},"kinsey":{"count":3,"weight":2},"mississippi":{"count":3,"weight":2},"collection":{"count":3,"weight":2},"lecture":{"count":3,"weight":2},"women":{"count":2,"weight":1},"monday":{"count":2,"weight":1},"coming":{"count":2,"weight":1},"week":{"count":2,"weight":1},"prize":{"count":2,"weight":1},"eyes":{"count":2,"weight":1},"documentary":{"count":2,"weight":1},"headlines":{"count":2,"weight":1},"weekend":{"count":2,"weight":1},"legal":{"count":2,"weight":1},"bulldog":{"count":2,"weight":1},"super":{"count":2,"weight":1}},"meta_kw":{"0":"higher education","1":" university","2":" college","3":" Mississippi State University","4":" engineering","5":" veterinary medicine","6":" architecture","7":" business","8":" teacher education","9":" agriculture","10":" forestry"}},"readability":{"flesch_kincaid_reading_ease":-48.6,"gunning_fog_score":39.5,"coleman_liau_index":17.3,"smog_index":26.6,"automated_readability_index":49.3}},"html":{"dom":{"counts":{"tags":{"a":84,"li":67,"comment":34,"div":24,"ul":13,"span":13,"meta":11,"img":11,"p":9,"link":7,"script":7,"h3":4,"h2":4,"br":3,"input":2,"center":2,"head":1,"form":1,"style":1,"html":1,"title":1,"body":1,"strong":1},"total":268},"body":{"count":9,"children":{"0":"div","1":"center","2":"p","3":"script","4":"script","5":"script","6":"comment","7":"script","8":"div"},"hash":"41f2f0ac34abc8effaea71d8285a3354","note":"I should be able to use this to get a feel for major redesigns?"}},"page_size":24483,"amazon":{"alexa":{"dmoz":{"0":"Reference","1":"Education","2":"Colleges and Universities","3":"North America","4":"United States","5":"Mississippi","6":"Mississippi State University"},"stats":{"speed":"561","links_in":"7229","reach":"34341","popularity":"26981","delta":"-4055"},"related_links":{"edu":{"http:\/\/www.mwsc.edu\/":{"HREF":"http:\/\/www.mwsc.edu\/","TITLE":"Missouri Western State College","PARSED_LINK":{"scheme":"http","host":"www.mwsc.edu","path":"\/"}},"http:\/\/www.usm.edu\/":{"HREF":"http:\/\/www.usm.edu\/","TITLE":"University of Southern Mississippi","PARSED_LINK":{"scheme":"http","host":"www.usm.edu","path":"\/"}},"http:\/\/www.olemiss.edu\/":{"HREF":"http:\/\/www.olemiss.edu\/","TITLE":"University of Mississippi","PARSED_LINK":{"scheme":"http","host":"www.olemiss.edu","path":"\/"}},"http:\/\/www.mvsu.edu\/":{"HREF":"http:\/\/www.mvsu.edu\/","TITLE":"Mississippi Valley State University","PARSED_LINK":{"scheme":"http","host":"www.mvsu.edu","path":"\/"}},"http:\/\/www.muw.edu\/":{"HREF":"http:\/\/www.muw.edu\/","TITLE":"Mississippi University for Women","PARSED_LINK":{"scheme":"http","host":"www.muw.edu","path":"\/"}},"http:\/\/www.msu.edu\/":{"HREF":"http:\/\/www.msu.edu\/","TITLE":"Michigan State University","PARSED_LINK":{"scheme":"http","host":"www.msu.edu","path":"\/"}},"http:\/\/www.montana.edu\/":{"HREF":"http:\/\/www.montana.edu\/","TITLE":"Montana State University","PARSED_LINK":{"scheme":"http","host":"www.montana.edu","path":"\/"}},"http:\/\/www.millsaps.edu\/":{"HREF":"http:\/\/www.millsaps.edu\/","TITLE":"Millsaps College","PARSED_LINK":{"scheme":"http","host":"www.millsaps.edu","path":"\/"}},"http:\/\/www.mc.edu\/":{"HREF":"http:\/\/www.mc.edu\/","TITLE":"Mississippi College","PARSED_LINK":{"scheme":"http","host":"www.mc.edu","path":"\/"}},"http:\/\/www.jsums.edu\/":{"HREF":"http:\/\/www.jsums.edu\/","TITLE":"Jackson State University","PARSED_LINK":{"scheme":"http","host":"www.jsums.edu","path":"\/"}}}},"keywords":{"0":"Mississippi State University"}}},"validation":{"w3c":{"status":"Invalid","errors":"15","warnings":"13","process_duration":1429430019.43}},"google":{"page_speed":{"kind":"pagespeedonline#result","id":"http:\/\/www.msstate.edu\/","responseCode":200,"title":"Mississippi State University","score":74,"pageStats":{"numberResources":38,"numberHosts":5,"totalRequestBytes":"3528","numberStaticResources":33,"htmlResponseBytes":"24693","cssResponseBytes":"15905","imageResponseBytes":"490915","javascriptResponseBytes":"103969","numberJsResources":5,"numberCssResources":2}},"page_rank":{"error":{"note":"Error Loading Google Data","code":"403","message":"Forbidden"}}}}},"icon":{"tiny":"http:\/\/www.msstate.edu\/favicon.ico","default":"http:\/\/www.msstate.edu\/favicon.ico"},"h1":null,"rss":{"0":{"href":"http:\/\/www.msstate.edu\/web\/rss_feeds\/2.0\/msu_news_rss_15.php","title":"News from Mississippi State University"},"1":{"href":"http:\/\/www.msstate.edu\/web\/rss_feeds\/2.0\/msu_calendar_today.php","title":"Today's Events at Mississippi State University"},"2":{"href":"http:\/\/www.msstate.edu\/web\/rss_feeds\/2.0\/msu_calendar_thisweek.php","title":"This Week's Events at Mississippi State University"},"3":{"href":"http:\/\/www.msstate.edu\/web\/rss_feeds\/2.0\/msu_announcements.php","title":"Mississippi State University Announcements"}},"screenshots":{"bluga":{"image_height":" 1114"}}},"see_also":{"builtwith":"http:\/\/builtwith.com\/www.msstate.edu","netcraft":"http:\/\/uptime.netcraft.com\/up\/graph?site=www.msstate.edu","alexa":"http:\/\/www.alexa.com\/data\/details\/main\/www.msstate.edu","compete":"http:\/\/siteanalytics.compete.com\/www.msstate.edu","quantcast":"https:\/\/www.quantcast.com\/www.msstate.edu","w3valid":"http:\/\/validator.w3.org\/check?uri=http%3A%2F%2Fwww.msstate.edu"},"process_duration":15.65}