{"url":{"scheme":"http","host":"www.thomas.edu","original":"http:\/\/www.thomas.edu","base":"http:\/\/www.thomas.edu","canonical":"http:\/\/www.thomas.edu\/"},"snapshot_info":{"ts":1429425194,"version":1,"date":"2015-04-19"},"domain":{"name":"thomas.edu","tld":"edu","ipv4":"209.222.215.135","whois":{"regrinfo":{"owner":{"name":"Thomas College","address":{"0":"180 West River Road","1":"Waterville, ME 04901-5097","2":"UNITED STATES"}},"admin":{"phone":"(207) 859-1124","email":"chris@thomas.edu","name":"Christopher H. Rhoda","address":{"0":"Vice President for Information Services and CIO","1":"Thomas College","2":"180 West River Road","3":"Waterville, ME 04901-5097","4":"UNITED STATES"}},"tech":{"phone":"(207) 859-1124","email":"chris@thomas.edu","name":"Christopher H. Rhoda","address":{"0":"Vice President for Information Services and CIO","1":"Thomas College","2":"180 West River Road","3":"Waterville, ME 04901-5097","4":"UNITED STATES"}},"domain":{"nserver":{"t16.thomas.edu":"66.252.45.9","t25.thomas.edu":"66.252.45.25","nameo.its.maine.edu":"130.111.32.11","namep.its.maine.edu":"130.111.130.7"},"created":"1994-03-09","changed":"2014-05-22","name":"thomas.edu"},"registered":"yes"}}},"server":{"server":{"raw":"Microsoft-IIS\/8.5"}},"response":{"time":0.6,"status":"200","protocol":"HTTP\/1.1","message":"OK","headers":{"content-type":"text\/html","last-modified":"Thu, 01 Jan 1970 00:00:00 GMT","server":"Microsoft-IIS\/8.5","x-powered-by":"PHP\/5.4.14","date":"Sun, 19 Apr 2015 06:33:16 GMT","connection":"close","content-length":"272154"}},"content":{"title":"Homepage - Thomas College","description":"Thomas is committed to your success. The world asks a lot of you in your professional lives, and thats why we\u00e2\u0080\u0099re here to help you meet its changing demands.","meta_tags":{"description":"Thomas is committed to your success. The world asks a lot of you in your professional lives, and thats why we\u00e2\u0080\u0099re here to help you meet its changing demands."},"analysis":{"text":{"counts":{"word":774,"sentence":39,"avg_sentance_words":21},"tags":{"word_weights":{"thomas":{"count":25,"weight":7},"college":{"count":16,"weight":5},"career":{"count":9,"weight":3},"admissions":{"count":8,"weight":3},"campus":{"count":7,"weight":2},"maine":{"count":6,"weight":2},"education":{"count":6,"weight":2},"alumni":{"count":5,"weight":2},"job":{"count":5,"weight":2},"help":{"count":5,"weight":2},"contact":{"count":5,"weight":2},"waterville":{"count":4,"weight":1},"programs":{"count":4,"weight":1},"aid":{"count":4,"weight":1},"learn":{"count":4,"weight":1},"select":{"count":4,"weight":1},"degree":{"count":4,"weight":1},"program":{"count":4,"weight":1},"donors":{"count":3,"weight":1},"graduates":{"count":3,"weight":1},"accepted":{"count":3,"weight":1},"student":{"count":3,"weight":1},"unity":{"count":3,"weight":1},"success":{"count":3,"weight":1},"study":{"count":3,"weight":1}}},"readability":{"flesch_kincaid_reading_ease":44.6,"gunning_fog_score":10.6,"coleman_liau_index":13.9,"smog_index":11,"automated_readability_index":12.6}},"html":{"dom":{"counts":{"tags":{"div":264,"a":115,"li":113,"option":50,"script":49,"comment":30,"ul":28,"input":25,"link":23,"span":13,"label":13,"img":13,"strong":12,"h1":12,"meta":11,"p":9,"h2":7,"select":5,"form":5,"fieldset":2,"address":1,"footer":1,"abbr":1,"head":1,"iframe":1,"br":1,"html":1,"header":1,"body":1,"title":1},"total":779},"body":{"count":3,"children":{"0":"div","1":"script","2":"comment"},"hash":"10c8eec6afbea176fe8700a5dcf417f4","note":"I should be able to use this to get a feel for major redesigns?"}},"page_size":272178,"amazon":{"alexa":{"dmoz":{},"stats":{"speed":"988","links_in":"415","reach":"846198","popularity":"749466","delta":"+132430"},"related_links":{"edu":{"http:\/\/www.uma.maine.edu\/":{"HREF":"http:\/\/www.uma.maine.edu\/","TITLE":"University of Maine at Augusta","PARSED_LINK":{"scheme":"http","host":"www.uma.maine.edu","path":"\/"}},"http:\/\/www.t-bird.edu\/":{"HREF":"http:\/\/www.t-bird.edu\/","TITLE":"Thunderbird, The American Graduate School of International Management","PARSED_LINK":{"scheme":"http","host":"www.t-bird.edu","path":"\/"}},"http:\/\/business.wm.edu\/":{"HREF":"http:\/\/business.wm.edu\/","TITLE":"College of William & Mary, Graduate School of Business","PARSED_LINK":{"scheme":"http","host":"business.wm.edu","path":"\/"}},"http:\/\/www.tju.edu\/":{"HREF":"http:\/\/www.tju.edu\/","TITLE":"Thomas Jefferson University","PARSED_LINK":{"scheme":"http","host":"www.tju.edu","path":"\/"}},"http:\/\/www.tesc.edu\/":{"HREF":"http:\/\/www.tesc.edu\/","TITLE":"Thomas Edison State College","PARSED_LINK":{"scheme":"http","host":"www.tesc.edu","path":"\/"}},"http:\/\/www.mainemaritime.edu\/":{"HREF":"http:\/\/www.mainemaritime.edu\/","TITLE":"Maine Maritime Academy","PARSED_LINK":{"scheme":"http","host":"www.mainemaritime.edu","path":"\/"}},"http:\/\/wwwcoles.kennesaw.edu\/lapd":{"HREF":"http:\/\/wwwcoles.kennesaw.edu\/lapd","TITLE":"Kennesaw State University","PARSED_LINK":{"scheme":"http","host":"wwwcoles.kennesaw.edu","path":"\/lapd"}},"http:\/\/www.wharton.upenn.edu\/":{"HREF":"http:\/\/www.wharton.upenn.edu\/","TITLE":"The Wharton School of The University of Pennsylvania","PARSED_LINK":{"scheme":"http","host":"www.wharton.upenn.edu","path":"\/"}},"http:\/\/www.webster.edu\/depts\/business":{"HREF":"http:\/\/www.webster.edu\/depts\/business","TITLE":"Webster University, School of Business and Technology","PARSED_LINK":{"scheme":"http","host":"www.webster.edu","path":"\/depts\/business"}},"http:\/\/www.weatherhead.cwru.edu\/acct\/macc\/MAcc_main.htm":{"HREF":"http:\/\/www.weatherhead.cwru.edu\/acct\/macc\/MAcc_main.htm","TITLE":"Case Western Reserve University, Weatherhead School of Management","PARSED_LINK":{"scheme":"http","host":"www.weatherhead.cwru.edu","path":"\/acct\/macc\/MAcc_main.htm"}},"http:\/\/www.ed.arizona.edu\/":{"HREF":"http:\/\/www.ed.arizona.edu\/","TITLE":"www.ed.arizona.edu\/","PARSED_LINK":{"scheme":"http","host":"www.ed.arizona.edu","path":"\/"}}}},"keywords":{"0":"Thomas College"}}},"validation":{"w3c":{"status":"Invalid","errors":"29","warnings":"4","process_duration":1429425223.35}},"google":{"page_speed":{"kind":"pagespeedonline#result","id":"http:\/\/www.thomas.edu\/","responseCode":200,"title":"Homepage - Thomas College","score":50,"pageStats":{"numberResources":78,"numberHosts":6,"totalRequestBytes":"7741","numberStaticResources":24,"htmlResponseBytes":"272827","cssResponseBytes":"212559","imageResponseBytes":"1874077","javascriptResponseBytes":"898595","otherResponseBytes":"192203","numberJsResources":35,"numberCssResources":13}},"page_rank":{"error":{"note":"Error Loading Google Data","code":"403","message":"Forbidden"}}}}},"icon":{"tiny":"http:\/\/www.thomas.edu\/wp-content\/themes\/thomas-college\/assets\/images\/favicon.ico","default":"http:\/\/www.thomas.edu\/assets\/images\/apple-touch-icon-iphone4.png","small":"http:\/\/www.thomas.edu\/assets\/images\/apple-touch-icon-iphone4.png"},"h1":"                                      Thomas                                  ","rss":{"0":{"href":"http:\/\/www.thomas.edu\/homepage\/feed\/","title":"Thomas College  &raquo; Homepage Comments Feed"}},"screenshots":{"bluga":{"image_height":" 3068"}}},"see_also":{"builtwith":"http:\/\/builtwith.com\/www.thomas.edu","netcraft":"http:\/\/uptime.netcraft.com\/up\/graph?site=www.thomas.edu","alexa":"http:\/\/www.alexa.com\/data\/details\/main\/www.thomas.edu","compete":"http:\/\/siteanalytics.compete.com\/www.thomas.edu","quantcast":"https:\/\/www.quantcast.com\/www.thomas.edu","w3valid":"http:\/\/validator.w3.org\/check?uri=http%3A%2F%2Fwww.thomas.edu"},"process_duration":38.81}