{"url":{"scheme":"http","host":"www.manhattanville.edu","original":"http:\/\/www.manhattanville.edu","base":"http:\/\/www.manhattanville.edu","redirect_url":"http:\/\/www.mville.edu","canonical":"\/content\/we-are-valiants"},"snapshot_info":{"ts":1429434383,"version":1,"date":"2015-04-19"},"domain":{"name":"manhattanville.edu","tld":"edu","ipv4":"162.159.240.193","whois":{"regrinfo":{"owner":{"name":"Manhattanville College","address":{"0":"2900 Purchase St.","1":"Purchase, NY 10577","2":"UNITED STATES"}},"admin":{"phone":"(914) 798-2709","email":"netops@mville.edu","name":"Network Operations","address":{"0":"Manhattanville College","1":"2900 Purchase Street","2":"Purchase, NY 10577","3":"UNITED STATES"}},"tech":{"phone":"(914) 798-2709","email":"netops@mville.edu","name":"Network Operations","address":{"0":"Manhattanville College","1":"2900 Purchase Street","2":"Purchase, NY 10577","3":"UNITED STATES"}},"domain":{"nserver":{"isla.ns.cloudflare.com":"173.245.58.119","will.ns.cloudflare.com":"173.245.59.149"},"created":"1996-02-20","changed":"2012-12-20","name":"manhattanville.edu"},"registered":"yes"}}},"server":{"server":{"raw":"nginx"}},"response":{"time":1.08,"status":"200","protocol":"HTTP\/1.1","message":"OK","headers":{"server":"nginx","x-varnish":"1229885410","vary":"Accept-Encoding, Cookie","cache-control":"no-cache, must-revalidate, post-check=0, pre-check=0","content-type":"text\/html; charset=utf-8","x-styx-build-sha":"7bb2d8bfad3980a9e38d528bfd8348ce61cc0c42","x-pantheon-styx-hostname":"styxe3d2930f","x-styx-version":"StyxGo","date":"Sun, 19 Apr 2015 09:06:22 GMT","link":"<\/node\/108>; rel=\"shortlink\",<\/content\/we-are-valiants>; rel=\"canonical\"","expires":"Sun, 19 Nov 1978 05:00:00 GMT","x-styx-req-id":"styx-77538cd412113e442cfc0df2d8e82ac3","content-language":"en","access-control-allow-origin":"*","x-generator":"Drupal 7 (http:\/\/drupal.org)","x-pantheon-endpoint":"2c1830ae-a962-46b8-844a-5cbd437bb525","via":"1.1 varnish","connection":"close","x-styx-build-date":"Wed Apr  8 00:26:15 UTC 2015","x-powered-by":"PHP\/5.3.29","x-styx-build-num":"904","age":"0"}},"content":{"title":"We Are Valiants | Manhattanville College","meta_tags":{"Generator":"Drupal 7 (http:\/\/drupal.org)","viewport":"width=device-width, initial-scale=1.0, maximum-scale=1.0, user-scalable=0"},"analysis":{"text":{"counts":{"word":1991,"sentence":78,"avg_sentance_words":27},"tags":{"word_weights":{"education":{"count":28,"weight":7},"manhattanville":{"count":23,"weight":6},"student":{"count":19,"weight":5},"school":{"count":17,"weight":5},"programs":{"count":16,"weight":4},"mville":{"count":16,"weight":4},"students":{"count":15,"weight":4},"campus":{"count":15,"weight":4},"life":{"count":14,"weight":4},"academic":{"count":13,"weight":4},"studies":{"count":13,"weight":4},"giving":{"count":13,"weight":4},"business":{"count":13,"weight":4},"undergraduate":{"count":13,"weight":4},"college":{"count":13,"weight":4},"center":{"count":12,"weight":3},"program":{"count":11,"weight":3},"services":{"count":11,"weight":3},"hours":{"count":10,"weight":3},"admissions":{"count":10,"weight":3},"institute":{"count":10,"weight":3},"graduate":{"count":10,"weight":3},"events":{"count":10,"weight":3},"information":{"count":10,"weight":3},"apply":{"count":10,"weight":3},"scholarships":{"count":9,"weight":3},"staff":{"count":9,"weight":3},"job":{"count":8,"weight":2},"ms":{"count":8,"weight":2},"learn":{"count":8,"weight":2},"alumni":{"count":8,"weight":2},"visit":{"count":8,"weight":2},"management":{"count":8,"weight":2},"session":{"count":8,"weight":2},"orientation":{"count":8,"weight":2},"+":{"count":8,"weight":2},"leadership":{"count":7,"weight":2},"meet":{"count":7,"weight":2},"aid":{"count":7,"weight":2},"summer":{"count":7,"weight":2},"community":{"count":7,"weight":2},"fair":{"count":7,"weight":2},"english":{"count":7,"weight":2},"office":{"count":7,"weight":2},"field":{"count":6,"weight":2},"min":{"count":6,"weight":2},"womens":{"count":6,"weight":2},"faculty":{"count":6,"weight":2},"event":{"count":6,"weight":2},"financial":{"count":6,"weight":2},"science":{"count":6,"weight":2},"writing":{"count":6,"weight":2},"degree":{"count":6,"weight":2},"experience":{"count":6,"weight":2},"president":{"count":6,"weight":2},"creative":{"count":6,"weight":2},"social":{"count":6,"weight":2},"fast":{"count":6,"weight":2},"scholarship":{"count":5,"weight":2},"reunion":{"count":5,"weight":2},"opportunities":{"count":5,"weight":2},"fees":{"count":5,"weight":2},"internship":{"count":5,"weight":2},"internships":{"count":5,"weight":2},"tuition":{"count":5,"weight":2},"castle":{"count":5,"weight":2},"news":{"count":5,"weight":2},"international":{"count":5,"weight":2},"start":{"count":5,"weight":2},"softball":{"count":5,"weight":2},"educational":{"count":5,"weight":2},"parents":{"count":5,"weight":2},"vs":{"count":5,"weight":2}}},"readability":{"flesch_kincaid_reading_ease":11.2,"gunning_fog_score":12,"coleman_liau_index":18.8,"smog_index":15.5,"automated_readability_index":19.8}},"html":{"dom":{"counts":{"tags":{"a":550,"li":473,"span":451,"div":220,"i":110,"ul":72,"p":72,"comment":43,"script":18,"h6":12,"input":12,"link":9,"h4":7,"h1":7,"blockquote":6,"h2":6,"br":5,"img":3,"meta":3,"strong":2,"nav":2,"header":2,"form":2,"footer":1,"head":1,"h3":1,"body":1,"title":1,"html":1},"total":2050},"body":{"count":7,"children":{"0":"comment","1":"header","2":"div","3":"comment","4":"div","5":"script","6":"script"},"hash":"3bcd4f91383f28874783ce1010d69cbf","note":"I should be able to use this to get a feel for major redesigns?"}},"page_size":130072,"amazon":{"alexa":{"stats":{"speed":null,"links_in":"181","reach":"4820433","popularity":"4812916","delta":"-13719382"},"related_links":{"edu":{"http:\/\/www.medaille.edu\/":{"HREF":"http:\/\/www.medaille.edu\/","TITLE":"Medaille College","PARSED_LINK":{"scheme":"http","host":"www.medaille.edu","path":"\/"}},"http:\/\/www.mville.edu\/education\/gradprograms.html":{"HREF":"http:\/\/www.mville.edu\/education\/gradprograms.html","TITLE":"School of Education Graduate Programs","PARSED_LINK":{"scheme":"http","host":"www.mville.edu","path":"\/education\/gradprograms.html"}},"http:\/\/www.mnsfld.edu\/":{"HREF":"http:\/\/www.mnsfld.edu\/","TITLE":"Mansfield University Of Pennsylvania","PARSED_LINK":{"scheme":"http","host":"www.mnsfld.edu","path":"\/"}},"http:\/\/www.mercynet.edu\/":{"HREF":"http:\/\/www.mercynet.edu\/","TITLE":"Mercy College","PARSED_LINK":{"scheme":"http","host":"www.mercynet.edu","path":"\/"}},"http:\/\/www.marymt.edu\/":{"HREF":"http:\/\/www.marymt.edu\/","TITLE":"Marymount College","PARSED_LINK":{"scheme":"http","host":"www.marymt.edu","path":"\/"}},"http:\/\/www.marist.edu\/":{"HREF":"http:\/\/www.marist.edu\/","TITLE":"Marist College","PARSED_LINK":{"scheme":"http","host":"www.marist.edu","path":"\/"}},"http:\/\/www.marietta.edu\/":{"HREF":"http:\/\/www.marietta.edu\/","TITLE":"Marietta College","PARSED_LINK":{"scheme":"http","host":"www.marietta.edu","path":"\/"}},"http:\/\/www.mankato.msus.edu\/":{"HREF":"http:\/\/www.mankato.msus.edu\/","TITLE":"Minnesota State University, Mankato Home","PARSED_LINK":{"scheme":"http","host":"www.mankato.msus.edu","path":"\/"}},"http:\/\/www.manhattan.edu\/":{"HREF":"http:\/\/www.manhattan.edu\/","TITLE":"Manhattan College","PARSED_LINK":{"scheme":"http","host":"www.manhattan.edu","path":"\/"}}}},"keywords":{"0":"Manhattanville College"}}},"validation":{"w3c":{"status":"Invalid","errors":"12","warnings":"1","process_duration":1429434405.94}},"google":{"page_speed":{"kind":"pagespeedonline#result","id":"http:\/\/www.mville.edu\/","responseCode":200,"title":"We Are Valiants | Manhattanville College","score":78,"pageStats":{"numberResources":60,"numberHosts":18,"totalRequestBytes":"9337","numberStaticResources":39,"htmlResponseBytes":"148115","cssResponseBytes":"522092","imageResponseBytes":"913031","javascriptResponseBytes":"1385652","otherResponseBytes":"163602","numberJsResources":17,"numberCssResources":8}},"page_rank":{"error":{"note":"Error Loading Google Data","code":"403","message":"Forbidden"}}}}},"icon":{"tiny":"http:\/\/www.mville.edu\/sites\/default\/files\/favicon.ico","default":"http:\/\/www.mville.edu\/sites\/default\/files\/favicon.ico"},"h1":"We Are Valiants","screenshots":{"bluga":{"image_height":" 4638"}}},"see_also":{"builtwith":"http:\/\/builtwith.com\/www.manhattanville.edu","netcraft":"http:\/\/uptime.netcraft.com\/up\/graph?site=www.manhattanville.edu","alexa":"http:\/\/www.alexa.com\/data\/details\/main\/www.manhattanville.edu","compete":"http:\/\/siteanalytics.compete.com\/www.manhattanville.edu","quantcast":"https:\/\/www.quantcast.com\/www.manhattanville.edu","w3valid":"http:\/\/validator.w3.org\/check?uri=http%3A%2F%2Fwww.manhattanville.edu"},"process_duration":27.26}