{"url":{"scheme":"http","host":"www.dillard.edu","original":"http:\/\/www.dillard.edu","base":"http:\/\/www.dillard.edu"},"snapshot_info":{"ts":1429424177,"version":1,"date":"2015-04-19"},"domain":{"name":"dillard.edu","tld":"edu","ipv4":"184.154.162.122","whois":{"regrinfo":{"owner":{"name":"Dillard University","address":{"0":"2601 Gentilly Blvd","1":"Information Technology Department","2":"New Orleans, LA 70122","3":"UNITED STATES"}},"admin":{"phone":"(504) 816-4872","email":"ckonyaole@dillard.edu","name":"Cedric Konyaole","address":{"0":"Director of Information Technology","1":"Dillard University","2":"2601 Gentilly Blvd","3":"Information Technology & Telecommunications Department","4":"New Orleans, LA 70122","5":"UNITED STATES"}},"tech":{"phone":"(504) 816-4576","email":"williams@dillard.edu","name":"Laranza Williams","address":{"0":"Network Infrastructure Manager","1":"Dillard University","2":"2601 Gentilly Blvd","3":"Information Technology & Telcommunications Department","4":"New Orleans, LA 70122","5":"UNITED STATES"}},"domain":{"nserver":{"pdns05.domaincontrol.com":"216.69.185.52","pdns06.domaincontrol.com":"208.109.255.52"},"created":"1995-02-06","changed":"2015-03-10","name":"dillard.edu"},"registered":"yes"}}},"server":{"server":{"raw":"Apache\/2.2.23 (Unix) mod_hive\/4.0 mod_ssl\/2.2.23 OpenSSL\/0.9.8e-fips-rhel5 mod_bwlimited\/1.4"},"cms":"Joomla! 1.5 - Open Source Content Management"},"response":{"time":0.66,"status":"200","protocol":"HTTP\/1.1","message":"OK","headers":{"date":"Sun, 19 Apr 2015 06:16:15 GMT","server":"Apache\/2.2.23 (Unix) mod_hive\/4.0 mod_ssl\/2.2.23 OpenSSL\/0.9.8e-fips-rhel5 mod_bwlimited\/1.4","x-powered-by":"PHP\/5.2.17","p3p":"CP=\"NOI ADM DEV PSAi COM NAV OUR OTRo STP IND DEM\"","expires":"Mon, 1 Jan 2001 00:00:00 GMT","cache-control":"post-check=0, pre-check=0","pragma":"no-cache","set-cookie":"4cb73700cda03a23d47f1058bc09019f=2c053441d6f84dc168c8cf06be9ed6a3; path=\/","last-modified":"Sun, 19 Apr 2015 06:16:15 GMT","host-header":"192fc2e7e50945beb8231a492d6a8024","connection":"close","content-type":"text\/html; charset=utf-8"}},"content":{"title":"dillard.edu","description":"The official site of Dillard University. Located in beautiful New Orleans.","meta_tags":{"robots":"index, follow","keywords":"Dillard, Dillard University, HBCU, New Orleans, Black College, Black University, University, Universities, School, higher education, education, black, learning, nursing, programs, alumni, communications, marketing, study, abroad, avenue, of, opportunity","description":"The official site of Dillard University. Located in beautiful New Orleans.","generator":"Joomla! 1.5 - Open Source Content Management","google-site-verification":"nnUpazckmABc2Uk0qRmXFsWu1ThqDAIFm8rbQHgysBo"},"analysis":{"text":{"counts":{"word":800,"sentence":33,"avg_sentance_words":25},"tags":{"word_weights":{"dillard":{"count":17,"weight":7},"office":{"count":10,"weight":4},"programs":{"count":9,"weight":4},"health":{"count":8,"weight":4},"student":{"count":8,"weight":4},"campus":{"count":7,"weight":3},"program":{"count":7,"weight":3},"university":{"count":7,"weight":3},"news":{"count":6,"weight":3},"public":{"count":6,"weight":3},"college":{"count":6,"weight":3},"nursing":{"count":5,"weight":2},"events":{"count":5,"weight":2},"staff":{"count":5,"weight":2},"admissions":{"count":5,"weight":2},"students":{"count":5,"weight":2},"alumni":{"count":4,"weight":2},"commencement":{"count":4,"weight":2},"financial":{"count":4,"weight":2},"president's":{"count":4,"weight":2},"athletics":{"count":4,"weight":2},"business":{"count":4,"weight":2},"center":{"count":4,"weight":2},"requirements":{"count":4,"weight":2},"educational":{"count":4,"weight":2},"contact":{"count":4,"weight":2}},"meta_kw":{"0":"Dillard","1":" Dillard University","2":" HBCU","3":" New Orleans","4":" Black College","5":" Black University","6":" University","7":" Universities","8":" School","9":" higher education","10":" education","11":" black","12":" learning","13":" nursing","14":" programs","15":" alumni","16":" communications","17":" marketing","18":" study","19":" abroad","20":" avenue","21":" of","22":" opportunity"}},"readability":{"flesch_kincaid_reading_ease":11.1,"gunning_fog_score":11.5,"coleman_liau_index":19.2,"smog_index":15.2,"automated_readability_index":19.1}},"html":{"dom":{"counts":{"tags":{"a":227,"span":187,"li":166,"p":53,"div":36,"img":33,"ul":28,"script":18,"comment":10,"link":9,"meta":8,"br":8,"input":5,"style":5,"table":2,"tr":2,"td":2,"title":2,"center":1,"form":1,"body":1,"xml:lang":1,"html":1},"total":796},"body":{"count":5,"children":{"0":"div","1":"div","2":"p","3":"p","4":"center"},"hash":"3ae1048a8e5e7a1b890b205e2b1af5c5","note":"I should be able to use this to get a feel for major redesigns?"}},"page_size":57664,"amazon":{"alexa":{"dmoz":{"0":"Reference","1":"Education","2":"Colleges and Universities","3":"North America","4":"United States","5":"Louisiana","6":"Dillard University"},"stats":{"speed":"968","links_in":"554","reach":"161051","popularity":"134313","delta":"-21473"},"related_links":{"edu":{"http:\/\/www.dickinson.edu\/":{"HREF":"http:\/\/www.dickinson.edu\/","TITLE":"Dickinson College","PARSED_LINK":{"scheme":"http","host":"www.dickinson.edu","path":"\/"}},"http:\/\/www.xula.edu\/":{"HREF":"http:\/\/www.xula.edu\/","TITLE":"Xula :: At Home In New Orleans","PARSED_LINK":{"scheme":"http","host":"www.xula.edu","path":"\/"}},"http:\/\/www.uno.edu\/":{"HREF":"http:\/\/www.uno.edu\/","TITLE":"University of New Orleans","PARSED_LINK":{"scheme":"http","host":"www.uno.edu","path":"\/"}},"http:\/\/www.lsus.edu\/":{"HREF":"http:\/\/www.lsus.edu\/","TITLE":"Louisiana State University at Shreveport","PARSED_LINK":{"scheme":"http","host":"www.lsus.edu","path":"\/"}},"http:\/\/www.lsu.edu\/":{"HREF":"http:\/\/www.lsu.edu\/","TITLE":"Louisiana State University","PARSED_LINK":{"scheme":"http","host":"www.lsu.edu","path":"\/"}},"http:\/\/www.loyno.edu\/":{"HREF":"http:\/\/www.loyno.edu\/","TITLE":"Loyola University","PARSED_LINK":{"scheme":"http","host":"www.loyno.edu","path":"\/"}},"http:\/\/www.latech.edu\/":{"HREF":"http:\/\/www.latech.edu\/","TITLE":"Louisiana Tech University","PARSED_LINK":{"scheme":"http","host":"www.latech.edu","path":"\/"}},"http:\/\/www.lacollege.edu\/":{"HREF":"http:\/\/www.lacollege.edu\/","TITLE":"Louisiana College","PARSED_LINK":{"scheme":"http","host":"www.lacollege.edu","path":"\/"}},"http:\/\/www.gram.edu\/":{"HREF":"http:\/\/www.gram.edu\/","TITLE":"Grambling State University","PARSED_LINK":{"scheme":"http","host":"www.gram.edu","path":"\/"}},"http:\/\/www.centenary.edu\/":{"HREF":"http:\/\/www.centenary.edu\/","TITLE":"Centenary College of Louisiana","PARSED_LINK":{"scheme":"http","host":"www.centenary.edu","path":"\/"}},"http:\/\/www.dcc.edu\/":{"HREF":"http:\/\/www.dcc.edu\/","TITLE":"www.dcc.edu\/","PARSED_LINK":{"scheme":"http","host":"www.dcc.edu","path":"\/"}}}},"keywords":{"0":"Dillard University"}}},"validation":{"w3c":{"status":"Invalid","errors":"47","warnings":"29","process_duration":1429424197.83}},"google":{"page_speed":{"kind":"pagespeedonline#result","id":"http:\/\/www.dillard.edu\/","responseCode":200,"title":"dillard.edu","score":57,"pageStats":{"numberResources":90,"numberHosts":21,"totalRequestBytes":"12171","numberStaticResources":49,"htmlResponseBytes":"58050","textResponseBytes":"596","cssResponseBytes":"16021","imageResponseBytes":"2271875","javascriptResponseBytes":"334195","otherResponseBytes":"23231","numberJsResources":11,"numberCssResources":5}},"page_rank":{"error":{"note":"Error Loading Google Data","code":"403","message":"Forbidden"}}}}},"icon":{"tiny":"http:\/\/www.dillard.edu\/favicon.ico","default":"http:\/\/www.dillard.edu\/favicon.ico"},"h1":null,"rss":{"0":{"href":"\/index.php?format=feed&amp;type=rss","title":"RSS 2.0"}},"screenshots":{"bluga":{"image_height":" 878"}}},"see_also":{"builtwith":"http:\/\/builtwith.com\/www.dillard.edu","netcraft":"http:\/\/uptime.netcraft.com\/up\/graph?site=www.dillard.edu","alexa":"http:\/\/www.alexa.com\/data\/details\/main\/www.dillard.edu","compete":"http:\/\/siteanalytics.compete.com\/www.dillard.edu","quantcast":"https:\/\/www.quantcast.com\/www.dillard.edu","w3valid":"http:\/\/validator.w3.org\/check?uri=http%3A%2F%2Fwww.dillard.edu"},"process_duration":25.09}