{"url":{"scheme":"http","host":"www.southernct.edu","original":"http:\/\/www.southernct.edu","base":"http:\/\/www.southernct.edu"},"snapshot_info":{"ts":1429416144,"version":1,"date":"2015-04-18"},"domain":{"name":"southernct.edu","tld":"edu","ipv4":"149.152.64.45","whois":{"regrinfo":{"owner":{"name":"Southern Connecticut State University","address":{"0":"501 Crescent Street","1":"New Haven, CT 06515","2":"UNITED STATES"}},"admin":{"phone":"(203) 392-6220","email":"hostmaster@southernct.edu","name":"Nicholas Brenckle","address":{"0":"Infrastructure Administrator","1":"Southern Connecticut State University","2":"501 Crescent Street","3":"New Haven, CT 06515","4":"UNITED STATES"}},"tech":{"phone":"(203) 392-6220","email":"hostmaster@southernct.edu","name":"SCSU Hostmaster","address":{"0":"Southern Connecticut State University","1":"501 Crescent Street","2":"New Haven, CT 06515","3":"UNITED STATES"}},"domain":{"nserver":{"ns1.southernct.edu":"149.152.64.4","ns2.southernct.edu":"149.152.64.5"},"created":"1997-09-11","changed":"2014-07-15","name":"southernct.edu"},"registered":"yes"}}},"server":{"server":{"raw":"Apache\/2.2.3 (CentOS)"}},"response":{"time":0.38,"status":"200","protocol":"HTTP\/1.1","message":"OK","headers":{"date":"Sun, 19 Apr 2015 04:02:23 GMT","server":"Apache\/2.2.3 (CentOS)","x-powered-by":"PHP\/5.3.3","connection":"close","content-type":"text\/html; charset=UTF-8"}},"content":{"title":"Southern Connecticut State University","analysis":{"text":{"counts":{"word":403,"sentence":15,"avg_sentance_words":31},"tags":{"word_weights":{"southern":{"count":8,"weight":3},"students":{"count":5,"weight":2},"student":{"count":5,"weight":2},"scsu":{"count":4,"weight":1},"university":{"count":4,"weight":1},"campus":{"count":4,"weight":1},"buley":{"count":4,"weight":1},"connecticut":{"count":4,"weight":1},"haven":{"count":4,"weight":1},"march":{"count":4,"weight":1},"read":{"count":3,"weight":1},"genocide":{"count":3,"weight":1},"library":{"count":3,"weight":1},"music":{"count":3,"weight":1},"section":{"count":3,"weight":1},"location":{"count":3,"weight":1},"check":{"count":2,"weight":1},"summer":{"count":2,"weight":1},"study":{"count":2,"weight":1},"environment":{"count":2,"weight":1},"barnard":{"count":2,"weight":1},"armenian":{"count":2,"weight":1},"session":{"count":2,"weight":1},"distinguished":{"count":2,"weight":1},"experience":{"count":2,"weight":1}}},"readability":{"flesch_kincaid_reading_ease":19.6,"gunning_fog_score":13.8,"coleman_liau_index":14.9,"smog_index":15,"automated_readability_index":18.5}},"html":{"dom":{"counts":{"tags":{"a":72,"li":53,"span":36,"comment":34,"div":28,"h3":27,"h4":25,"br":10,"script":8,"img":8,"ul":8,"section":5,"p":5,"link":4,"nav":3,"meta":3,"strong":1,"footer":1,"h1":1,"h2":1,"form":1,"body":1,"title":1,"head":1,"html":1,"label":1,"input":1},"total":306},"body":{"count":8,"children":{"0":"p","1":"section","2":"section","3":"section","4":"section","5":"div","6":"footer","7":"div"},"hash":"e0b73c80a212464c0d59c2d5cd865a60","note":"I should be able to use this to get a feel for major redesigns?"}},"page_size":20648,"amazon":{"alexa":{"dmoz":{"0":"Reference","1":"Education","2":"Colleges and Universities","3":"North America","4":"United States","5":"Connecticut","6":"Connecticut State Colleges and Universities","7":"Southern"},"stats":{"speed":"709","links_in":"1333","reach":"126433","popularity":"110560","delta":"+11380"},"related_links":{"org":{"http:\/\/ctmentor.org\/":{"HREF":"http:\/\/ctmentor.org\/","TITLE":"ConnecticutMentor","PARSED_LINK":{"scheme":"http","host":"ctmentor.org","path":"\/"}}},"gov":{"http:\/\/ct.gov\/":{"HREF":"http:\/\/ct.gov\/","TITLE":"ConneCT","PARSED_LINK":{"scheme":"http","host":"ct.gov","path":"\/"}}},"edu":{"http:\/\/www.cga.edu\/":{"HREF":"http:\/\/www.cga.edu\/","TITLE":"United States Coast Guard Academy","PARSED_LINK":{"scheme":"http","host":"www.cga.edu","path":"\/"}},"http:\/\/www.yale.edu\/":{"HREF":"http:\/\/www.yale.edu\/","TITLE":"Yale University | Yale University","PARSED_LINK":{"scheme":"http","host":"www.yale.edu","path":"\/"}},"http:\/\/www.subr.edu\/":{"HREF":"http:\/\/www.subr.edu\/","TITLE":"Southern University at Baton Rouge","PARSED_LINK":{"scheme":"http","host":"www.subr.edu","path":"\/"}},"http:\/\/www.snu.edu\/":{"HREF":"http:\/\/www.snu.edu\/","TITLE":"Southern Nazarene University","PARSED_LINK":{"scheme":"http","host":"www.snu.edu","path":"\/"}},"http:\/\/www.semo.edu\/":{"HREF":"http:\/\/www.semo.edu\/","TITLE":"Southeast Missouri State University","PARSED_LINK":{"scheme":"http","host":"www.semo.edu","path":"\/"}},"http:\/\/www.selu.edu\/":{"HREF":"http:\/\/www.selu.edu\/","TITLE":"Southeastern Louisiana University","PARSED_LINK":{"scheme":"http","host":"www.selu.edu","path":"\/"}},"http:\/\/www.sct.edu\/":{"HREF":"http:\/\/www.sct.edu\/","TITLE":"Sct","PARSED_LINK":{"scheme":"http","host":"www.sct.edu","path":"\/"}},"http:\/\/www.ccsu.edu\/":{"HREF":"http:\/\/www.ccsu.edu\/","TITLE":"Central Connecticut State University","PARSED_LINK":{"scheme":"http","host":"www.ccsu.edu","path":"\/"}},"http:\/\/www.southernct.edu\/":{"HREF":"http:\/\/www.southernct.edu\/","TITLE":"www.southernct.edu\/","PARSED_LINK":{"scheme":"http","host":"www.southernct.edu","path":"\/"}}}},"keywords":{"0":"Connecticut State University System"}}},"validation":{"w3c":{"status":"Invalid","errors":"10","warnings":"4","process_duration":1429416163.44}},"google":{"page_speed":{"kind":"pagespeedonline#result","id":"http:\/\/www.southernct.edu\/","responseCode":200,"title":"Southern Connecticut State University","score":72,"pageStats":{"numberResources":30,"numberHosts":4,"totalRequestBytes":"2636","numberStaticResources":25,"htmlResponseBytes":"20818","cssResponseBytes":"70952","imageResponseBytes":"834741","javascriptResponseBytes":"125023","otherResponseBytes":"63001","numberJsResources":5,"numberCssResources":3}},"page_rank":{"error":{"note":"Error Loading Google Data","code":"403","message":"Forbidden"}}}}},"icon":{"tiny":"http:\/\/www.southernct.edu\/files\/images\/favicon.ico","default":"http:\/\/www.southernct.edu\/files\/images\/favicon.ico"},"h1":"Dynamic, Diverse, Dedicated to Student Success.","screenshots":{"bluga":{"image_height":" 1682"}}},"see_also":{"builtwith":"http:\/\/builtwith.com\/www.southernct.edu","netcraft":"http:\/\/uptime.netcraft.com\/up\/graph?site=www.southernct.edu","alexa":"http:\/\/www.alexa.com\/data\/details\/main\/www.southernct.edu","compete":"http:\/\/siteanalytics.compete.com\/www.southernct.edu","quantcast":"https:\/\/www.quantcast.com\/www.southernct.edu","w3valid":"http:\/\/validator.w3.org\/check?uri=http%3A%2F%2Fwww.southernct.edu"},"process_duration":21.66}